{"cameraMode":{"drawMode":0,"name":"Shaded","section":"Shading Mode"},"sceneLighting":true,"audioPlay":false,"sceneViewState":{"m_AlwaysRefresh":false,"showFog":true,"showSkybox":true,"showFlares":true,"showImageEffects":true,"showParticleSystems":true,"showVisualEffectGraphs":true,"m_FxEnabled":true},"in2DMode":false,"pivot":{"x":4.534915447235107,"y":-1.4994535446166993,"z":-2.874068260192871},"rotation":{"x":-0.2881845235824585,"y":-0.05397383123636246,"z":0.0162716843187809,"w":-0.9559147357940674},"size":19.657623291015626,"orthographic":false}